ftm_lakehouse/__init__.py
ftm_lakehouse/api/__init__.py
ftm_lakehouse/api/auth.py
ftm_lakehouse/api/main.py
ftm_lakehouse/api/util.py
ftm_lakehouse/catalog.py
ftm_lakehouse/cli.py
ftm_lakehouse/core/__init__.py
ftm_lakehouse/core/config.py
ftm_lakehouse/core/conventions/__init__.py
ftm_lakehouse/core/conventions/path.py
ftm_lakehouse/core/conventions/tag.py
ftm_lakehouse/core/settings.py
ftm_lakehouse/dataset.py
ftm_lakehouse/exceptions.py
ftm_lakehouse/helpers/dataset.py
ftm_lakehouse/helpers/file.py
ftm_lakehouse/helpers/serialization.py
ftm_lakehouse/helpers/statements.py
ftm_lakehouse/lake.py
ftm_lakehouse/logic/__init__.py
ftm_lakehouse/logic/entities.py
ftm_lakehouse/logic/mappings.py
ftm_lakehouse/model/__init__.py
ftm_lakehouse/model/crud.py
ftm_lakehouse/model/dataset.py
ftm_lakehouse/model/file.py
ftm_lakehouse/model/job.py
ftm_lakehouse/model/mapping.py
ftm_lakehouse/operation/__init__.py
ftm_lakehouse/operation/base.py
ftm_lakehouse/operation/crawl.py
ftm_lakehouse/operation/export.py
ftm_lakehouse/operation/mapping.py
ftm_lakehouse/operation/optimize.py
ftm_lakehouse/repository/__init__.py
ftm_lakehouse/repository/archive.py
ftm_lakehouse/repository/base.py
ftm_lakehouse/repository/entities.py
ftm_lakehouse/repository/factories.py
ftm_lakehouse/repository/job.py
ftm_lakehouse/repository/mapping.py
ftm_lakehouse/storage/__init__.py
ftm_lakehouse/storage/base.py
ftm_lakehouse/storage/blob.py
ftm_lakehouse/storage/file.py
ftm_lakehouse/storage/journal.py
ftm_lakehouse/storage/parquet.py
ftm_lakehouse/storage/queue.py
ftm_lakehouse/storage/tags.py
ftm_lakehouse/storage/text.py
ftm_lakehouse/storage/versions.py
ftm_lakehouse/util.py
ftm_lakehouse-0.1.2.dist-info/METADATA
ftm_lakehouse-0.1.2.dist-info/WHEEL
ftm_lakehouse-0.1.2.dist-info/entry_points.txt
ftm_lakehouse-0.1.2.dist-info/licenses/LICENSE
ftm_lakehouse-0.1.2.dist-info/licenses/NOTICE
ftm_lakehouse-0.1.2.dist-info/RECORD
