Metadata-Version: 2.4
Name: ftm-lakehouse
Version: 0.1.2
Summary: Data standard, storage and retrieval for structured and unstructured FollowTheMoney data
License: AGPLv3+
License-File: LICENSE
License-File: NOTICE
Author: Data and Research Center
Author-email: hi@dataresearchcenter.org
Requires-Python: >=3.11,<4
Classifier: License :: OSI Approved :: GNU Affero General Public License v3 or later (AGPLv3+)
Classifier: Intended Audience :: Developers
Classifier: Operating System :: OS Independent
Classifier: Programming Language :: Python
Classifier: Programming Language :: Python :: 3.11
Classifier: Programming Language :: Python :: 3.12
Classifier: Programming Language :: Python :: 3.13
Classifier: Programming Language :: Python :: 3.14
Provides-Extra: api
Requires-Dist: anystore (>=0.4.3,<0.5.0)
Requires-Dist: fastapi (>=0.115.6,<0.116.0) ; extra == "api"
Requires-Dist: followthemoney (>=4.5.0,<5.0.0)
Requires-Dist: ftmq[lake] (>=4.5.0,<5.0.0)
Requires-Dist: jinja2 (>=3.1.5,<4.0.0)
Requires-Dist: pyjwt (>=2.10.1,<3.0.0) ; extra == "api"
Requires-Dist: uvicorn (>=0.34.0,<0.35.0) ; extra == "api"
Project-URL: Documentation, https://openaleph.org/docs/lib/ftm-lakehouse
Project-URL: Homepage, https://openaleph.org/docs/lib/ftm-lakehouse
Project-URL: Issues, https://github.com/openaleph/ftm-lakehouse/issues
Project-URL: Repository, https://github.com/openaleph/ftm-lakehouse
